dding/__init__.py
dding/cmdline.py
dding/notify.py
dding-0.1.10.dist-info/METADATA
dding-0.1.10.dist-info/WHEEL
dding-0.1.10.dist-info/entry_points.txt
dding-0.1.10.dist-info/top_level.txt
dding-0.1.10.dist-info/RECORD
