Metadata-Version: 2.4
Name: dding
Version: 0.1.10
Summary: 通知机器人.
Home-page: https://github.com/charlessoft/dding
Author: charlessoft
Author-email: charlessoft@qq.com
License: MIT
Keywords: dding
Requires-Dist: six
Dynamic: author
Dynamic: author-email
Dynamic: description
Dynamic: home-page
Dynamic: keywords
Dynamic: license
Dynamic: requires-dist
Dynamic: summary
